bins/__init__.py
bins/find_instabilities.py
ant_instability_detection-101.0.0.dist-info/METADATA
ant_instability_detection-101.0.0.dist-info/WHEEL
ant_instability_detection-101.0.0.dist-info/entry_points.txt
ant_instability_detection-101.0.0.dist-info/top_level.txt
ant_instability_detection-101.0.0.dist-info/RECORD
