Metadata-Version: 2.4
Name: ant_instability_detection
Version: 101.0.0
Summary: Ensure there is not instability in the ant protocol.
Author-email: Bastien Legras <Bastien.Legras@proton.me>
License: MIT
Requires-Python: >=3.7
